webbie/__init__.py
webbie-0.0.2.dist-info/METADATA
webbie-0.0.2.dist-info/WHEEL
webbie-0.0.2.dist-info/top_level.txt
webbie-0.0.2.dist-info/RECORD
