Metadata-Version: 2.1
Name: webbie
Version: 0.0.2
Summary: A framework for building web applications in pure python 
Home-page: https://github.com/Advik-B/webbie
Author: Advik
Author-email: <advik.b@gmail.com>
Keywords: Web,PythonWeb,WebPython,Webdev
Classifier: Intended Audience :: Developers
Classifier: Programming Language :: Python :: 3
Classifier: License :: OSI Approved :: MIT License
Classifier: Operating System :: OS Independent
Requires-Dist: flask
